COPYING
COPYING.lesser
MANIFEST.in
NOTICE
README.md
requirements.txt
setup.cfg
setup.py
compiler/__init__.py
compiler/api/__init__.py
compiler/api/compiler.py
compiler/api/source/auth_key.tl
compiler/api/source/main_api.tl
compiler/api/source/sys_msgs.tl
compiler/api/template/combinator.txt
compiler/api/template/type.txt
compiler/docs/__init__.py
compiler/docs/compiler.py
compiler/docs/template/page.txt
compiler/docs/template/toctree.txt
compiler/errors/__init__.py
compiler/errors/compiler.py
compiler/errors/sort.py
compiler/errors/source/303_SEE_OTHER.tsv
compiler/errors/source/400_BAD_REQUEST.tsv
compiler/errors/source/401_UNAUTHORIZED.tsv
compiler/errors/source/403_FORBIDDEN.tsv
compiler/errors/source/406_NOT_ACCEPTABLE.tsv
compiler/errors/source/420_FLOOD.tsv
compiler/errors/source/500_INTERNAL_SERVER_ERROR.tsv
compiler/errors/source/503_SERVICE_UNAVAILABLE.tsv
compiler/errors/template/class.txt
compiler/errors/template/sub_class.txt
oldpyro/__init__.py
oldpyro/client.py
oldpyro/dispatcher.py
oldpyro/emoji.py
oldpyro/file_id.py
oldpyro/filters.py
oldpyro/mime_types.py
oldpyro/py.typed
oldpyro/scaffold.py
oldpyro/sync.py
oldpyro/syncer.py
oldpyro/utils.py
oldpyro.egg-info/PKG-INFO
oldpyro.egg-info/SOURCES.txt
oldpyro.egg-info/dependency_links.txt
oldpyro.egg-info/not-zip-safe
oldpyro.egg-info/requires.txt
oldpyro.egg-info/top_level.txt
oldpyro/connection/__init__.py
oldpyro/connection/connection.py
oldpyro/connection/transport/__init__.py
oldpyro/connection/transport/tcp/__init__.py
oldpyro/connection/transport/tcp/tcp.py
oldpyro/connection/transport/tcp/tcp_abridged.py
oldpyro/connection/transport/tcp/tcp_abridged_o.py
oldpyro/connection/transport/tcp/tcp_full.py
oldpyro/connection/transport/tcp/tcp_intermediate.py
oldpyro/connection/transport/tcp/tcp_intermediate_o.py
oldpyro/crypto/__init__.py
oldpyro/crypto/aes.py
oldpyro/crypto/mtproto.py
oldpyro/crypto/prime.py
oldpyro/crypto/rsa.py
oldpyro/errors/__init__.py
oldpyro/errors/rpc_error.py
oldpyro/handlers/__init__.py
oldpyro/handlers/callback_query_handler.py
oldpyro/handlers/chat_join_request_handler.py
oldpyro/handlers/chat_member_updated_handler.py
